janis_unix/__init__.py
janis_unix/__meta__.py
janis_unix/data_types/__init__.py
janis_unix/data_types/csv.py
janis_unix/data_types/gunzipped.py
janis_unix/data_types/html.py
janis_unix/data_types/json.py
janis_unix/data_types/tarfile.py
janis_unix/data_types/text.py
janis_unix/data_types/tsv.py
janis_unix/data_types/zipfile.py
janis_unix/tools/__init__.py
janis_unix/tools/awk.py
janis_unix/tools/cat.py
janis_unix/tools/compile.py
janis_unix/tools/echo.py
janis_unix/tools/gatherfilestofolder.py
janis_unix/tools/hello.py
janis_unix/tools/localisefolder.py
janis_unix/tools/md5sum.py
janis_unix/tools/sleep.py
janis_unix/tools/tar.py
janis_unix/tools/transposetsv.py
janis_unix/tools/uncompressarchive.py
janis_unix/tools/unixtool.py
janis_unix/tools/untar.py
janis_pipelines.unix-0.12.0.dist-info/LICENSE
janis_pipelines.unix-0.12.0.dist-info/METADATA
janis_pipelines.unix-0.12.0.dist-info/WHEEL
janis_pipelines.unix-0.12.0.dist-info/entry_points.txt
janis_pipelines.unix-0.12.0.dist-info/top_level.txt
janis_pipelines.unix-0.12.0.dist-info/RECORD
