Metadata-Version: 2.1
Name: janis-pipelines.unix
Version: 0.12.0
Summary: Unix tools and data types for Janis
Home-page: UNKNOWN
Author: Michael Franklin, Evan Thomas, Mohammad Bhuyan
Author-email: michael.franklin@petermac.org
License: GNU
Keywords: pipelines,bioinformatics,workflows
Platform: UNKNOWN
Classifier: Development Status :: 2 - Pre-Alpha
Classifier: Intended Audience :: Developers
Classifier: Intended Audience :: Science/Research
Classifier: Topic :: Scientific/Engineering
Classifier: Topic :: Scientific/Engineering :: Bio-Informatics
Requires-Dist: janis-pipelines.core (>=0.10.7)
Provides-Extra: ci
Requires-Dist: keyring (==21.4.0) ; extra == 'ci'
Requires-Dist: setuptools ; extra == 'ci'
Requires-Dist: wheel ; extra == 'ci'
Requires-Dist: twine ; extra == 'ci'
